digitalis/__init__.py
digitalis/__main__.py
digitalis/app.py
digitalis/app.tcss
digitalis/exceptions.py
digitalis/grammar/README.md
digitalis/grammar/__init__.py
digitalis/grammar/grammar.lark
digitalis/grammar/parser.py
digitalis/grammar/query.py
digitalis/grammar/test_parser.py
digitalis/grammar/test_query.py
digitalis/py.typed
digitalis/reader/README.md
digitalis/reader/__init__.py
digitalis/reader/mcap/__init__.py
digitalis/reader/mcap/mcap_read.py
digitalis/reader/mcap/mcap_read_preloading.py
digitalis/reader/mcap/source.py
digitalis/reader/source.py
digitalis/reader/types.py
digitalis/reader/websocket/__init__.py
digitalis/reader/websocket/source.py
digitalis/screens/__init__.py
digitalis/screens/data.py
digitalis/screens/main.py
digitalis/turbo.py
digitalis/ui/__init__.py
digitalis/ui/datapanel.py
digitalis/ui/panels/__init__.py
digitalis/ui/panels/base.py
digitalis/ui/panels/diagnostics.py
digitalis/ui/panels/image.py
digitalis/ui/panels/interactive_base.py
digitalis/ui/panels/navsat_fix.py
digitalis/ui/panels/occupancy_grid.py
digitalis/ui/panels/pointcloud.py
digitalis/ui/panels/pointcloud_renderer.py
digitalis/ui/panels/raw.py
digitalis/ui/panels/tf.py
digitalis/ui/search.py
digitalis/ui/timecontrol.py
digitalis/utilities.py
digitalis-0.6.0.dist-info/WHEEL
digitalis-0.6.0.dist-info/entry_points.txt
digitalis-0.6.0.dist-info/METADATA
digitalis-0.6.0.dist-info/RECORD
