Metadata-Version: 2.3
Name: digitalis
Version: 0.6.0
Summary: Add your description here
Requires-Dist: cachetools>=6.1.0
Requires-Dist: lark>=1.2.2
Requires-Dist: mcap>=1.3.0
Requires-Dist: mcap-ros2-support>=0.5.5
Requires-Dist: pointcloud2>=0.2.3
Requires-Dist: textual>=5.1.1
Requires-Dist: textual-image>=0.8.3
Requires-Dist: textual-slider>=0.2.0
Requires-Dist: textual-speedups>=0.2.0 ; platform_machine == 'arm64' and sys_platform == 'darwin'
Requires-Dist: websockets>=15.0.1
Requires-Python: >=3.10
